consepsimdisc/__init__.py
consepsimdisc/disc.py
consepsimdisc/algoritmos/__init__.py
consepsimdisc/algoritmos/aproximacion.py
consepsimdisc/algoritmos/determistas.py
consepsimdisc/algoritmos/generic.py
consepsimdisc/algoritmos/paralelos.py
consepsimdisc-0.0.4.dist-info/METADATA
consepsimdisc-0.0.4.dist-info/WHEEL
consepsimdisc-0.0.4.dist-info/top_level.txt
consepsimdisc-0.0.4.dist-info/RECORD
