Metadata-Version: 2.1
Name: consepsimdisc
Version: 0.0.4
Summary: Library to compute conceptual distance by using DIS-C method
Home-page: https://gitlab.com/TebanMT
Author: Esteban Mendiola Tellez
Author-email: mendiola_esteban@outlook.com
License: MIT
Platform: UNKNOWN
Requires-Dist: networkx
Requires-Dist: numpy
Requires-Dist: nltk
